aws_cdk/asset_kubectl_v20/_jsii/__init__.py
aws_cdk/asset_kubectl_v20/_jsii/asset-kubectl-v20@2.1.2.jsii.tgz
aws_cdk.asset_kubectl_v20-2.1.2.dist-info/LICENSE
aws_cdk.asset_kubectl_v20-2.1.2.dist-info/METADATA
aws_cdk.asset_kubectl_v20-2.1.2.dist-info/NOTICE
aws_cdk.asset_kubectl_v20-2.1.2.dist-info/WHEEL
aws_cdk.asset_kubectl_v20-2.1.2.dist-info/top_level.txt
aws_cdk.asset_kubectl_v20-2.1.2.dist-info/RECORD
